padar/__init__.py
padar/dar.py
padar/helper.py
padar/mdcas.py
padar/pad.py
padar/reu.py
padar/api/__init__.py
padar/api/dataset.py
padar/api/date_time.py
padar/api/detect_peaks.py
padar/api/filter.py
padar/api/interpolate.py
padar/api/numeric_feature.py
padar/api/numeric_transformation.py
padar/api/utils.py
padar/api/windowing.py
padar/api/accelerometer/__init__.py
padar/api/accelerometer/_calibraxis.py
padar/api/accelerometer/calibrator.py
padar/api/accelerometer/static_finder.py
padar/api/helpers/__init__.py
padar/api/helpers/importer.py
padar/api/helpers/parser.py
padar/api/helpers/summarizer.py
padar/api/helpers/visualizer.py
padar/apps/__init__.py
padar/apps/data_quality_check.py
padar/debug/__init__.py
padar/debug/debug_calibrator.py
padar/debug/debug_parser.py
padar/debug/debug_process.py
padar/debug/debug_summarize.py
padar/debug/debug_utils.py
padar/scripts/AccelerometerCalibrator.py
padar/scripts/AccelerometerPreprocessor.py
padar/scripts/AnnotationConcatenator.py
padar/scripts/BaseProcessor.py
padar/scripts/ClassLabelAssigner.py
padar/scripts/Copier.py
padar/scripts/ManualOrientationNormalizer.py
padar/scripts/OrientationFeatureComputer.py
padar/scripts/SensorClipper.py
padar/scripts/SensorConcatenator.py
padar/scripts/SensorFilter.py
padar/scripts/SensorResampler.py
padar/scripts/SensorSummarizer.py
padar/scripts/SensorTransformer.py
padar/scripts/SessionExtractor.py
padar/scripts/StaticFinder.py
padar/scripts/StaticVectorFinder.py
padar/scripts/TimeFreqFeatureComputer.py
padar/scripts/TimestampOffset.py
padar/scripts/TimestampSyncer.py
padar/scripts/__init__.py
padar/scripts/camspades_lab/ClassLabelAssigner.py
padar/scripts/camspades_lab/__init__.py
padar/scripts/models/BaseModel.py
padar/scripts/models/SVMClassifier.py
padar/scripts/models/__init__.py
padar/scripts/models/MDCAS/MDCASClassifier.py
padar/scripts/models/MDCAS/__init__.py
padar-1.1.2.dist-info/LICENSE.txt
padar-1.1.2.dist-info/METADATA
padar-1.1.2.dist-info/RECORD
padar-1.1.2.dist-info/WHEEL
padar-1.1.2.dist-info/entry_points.txt
padar-1.1.2.dist-info/top_level.txt
