Metadata-Version: 2.1
Name: padar
Version: 1.1.2
Summary: Processing Accelerometer Data and Do Activity Recognition
Home-page: https://github.com/qutang/padar
Author: Qu Tang
Author-email: tqshelly@gmail.com
License: MIT
Project-URL: Source, https://github.com/qutang/padar/
Project-URL: Tracker, https://github.com/qutang/padar/issues
Keywords: data mhealth accelerometer machine learning
Platform: UNKNOWN
Classifier: Development Status :: 3 - Alpha
Classifier: Intended Audience :: Developers
Classifier: Intended Audience :: Science/Research
Classifier: Topic :: Software Development
Classifier: Topic :: Scientific/Engineering
Classifier: License :: OSI Approved :: MIT License
Classifier: Programming Language :: Python :: 3
Requires-Python: >=3
Requires-Dist: Click
Requires-Dist: jinja2
Requires-Dist: pweave
Requires-Dist: pandas
Requires-Dist: numpy
Requires-Dist: scipy
Requires-Dist: pathos
Requires-Dist: transforms3d
Requires-Dist: scikit-learn
Requires-Dist: altair
Requires-Dist: padar-converter
